lazy_decorators/__init__.py
lazy_decorators/dynamic_cache.py
lazy_decorators/dynamic_cache_thread_safe.py
lazy_decorators-1.0.2.dist-info/METADATA
lazy_decorators-1.0.2.dist-info/WHEEL
lazy_decorators-1.0.2.dist-info/top_level.txt
lazy_decorators-1.0.2.dist-info/RECORD
