Metadata-Version: 2.4
Name: lazy-decorators
Version: 1.0.2
Summary: Decorators to define lazy methods and functions
Home-page: https://github.com/ehsankarbasian/lazy_decorators
Author: Ehsan Karbasian
Author-email: ehsan.karbasian@gmail.com
Classifier: Programming Language :: Python :: 3
Classifier: License :: OSI Approved :: MIT License
Classifier: Operating System :: OS Independent
Requires-Python: >=3.6
Dynamic: author
Dynamic: author-email
Dynamic: classifier
Dynamic: description
Dynamic: description-content-type
Dynamic: home-page
Dynamic: requires-python
Dynamic: summary
